Mongodb36ZhongwenWendang/README.md
Mongodb36ZhongwenWendang/__init__.py
Mongodb36ZhongwenWendang/__main__.py
Mongodb36ZhongwenWendang/file.epub
Mongodb36ZhongwenWendang/index.html
Mongodb36ZhongwenWendang/css/__init__.py
Mongodb36ZhongwenWendang/css/annotations.css
Mongodb36ZhongwenWendang/css/main.css
Mongodb36ZhongwenWendang/css/normalize.css
Mongodb36ZhongwenWendang/css/popup.css
Mongodb36ZhongwenWendang/font/__init__.py
Mongodb36ZhongwenWendang/font/fontello.eot
Mongodb36ZhongwenWendang/font/fontello.svg
Mongodb36ZhongwenWendang/font/fontello.ttf
Mongodb36ZhongwenWendang/font/fontello.woff
Mongodb36ZhongwenWendang/img/__init__.py
Mongodb36ZhongwenWendang/img/annotator-glyph-sprite.png
Mongodb36ZhongwenWendang/img/annotator-icon-sprite.png
Mongodb36ZhongwenWendang/img/apple-touch-icon.png
Mongodb36ZhongwenWendang/img/cancelfullscreen.png
Mongodb36ZhongwenWendang/img/close.png
Mongodb36ZhongwenWendang/img/fullscreen.png
Mongodb36ZhongwenWendang/img/loader.gif
Mongodb36ZhongwenWendang/img/menu-icon.png
Mongodb36ZhongwenWendang/img/save.png
Mongodb36ZhongwenWendang/img/saved.png
Mongodb36ZhongwenWendang/img/settings-s.png
Mongodb36ZhongwenWendang/img/settings.png
Mongodb36ZhongwenWendang/img/star.png
Mongodb36ZhongwenWendang/js/__init__.py
Mongodb36ZhongwenWendang/js/epub.js
Mongodb36ZhongwenWendang/js/epub.min.js
Mongodb36ZhongwenWendang/js/epub.min.map
Mongodb36ZhongwenWendang/js/hooks.min.js
Mongodb36ZhongwenWendang/js/hooks.min.map
Mongodb36ZhongwenWendang/js/reader.js
Mongodb36ZhongwenWendang/js/reader.js.map
Mongodb36ZhongwenWendang/js/reader.min.js
Mongodb36ZhongwenWendang/js/reader.min.map
Mongodb36ZhongwenWendang/js/hooks/__init__.py
Mongodb36ZhongwenWendang/js/hooks/extensions/__init__.py
Mongodb36ZhongwenWendang/js/hooks/extensions/highlight.js
Mongodb36ZhongwenWendang/js/libs/__init__.py
Mongodb36ZhongwenWendang/js/libs/jquery.min.js
Mongodb36ZhongwenWendang/js/libs/localforage.min.js
Mongodb36ZhongwenWendang/js/libs/screenfull.js
mongodb_3_6_zhongwen_wendang-2024.3.5.0.dist-info/METADATA
mongodb_3_6_zhongwen_wendang-2024.3.5.0.dist-info/WHEEL
mongodb_3_6_zhongwen_wendang-2024.3.5.0.dist-info/entry_points.txt
mongodb_3_6_zhongwen_wendang-2024.3.5.0.dist-info/top_level.txt
mongodb_3_6_zhongwen_wendang-2024.3.5.0.dist-info/RECORD
